twofactorauthcli/__init__.py
twofactorauthcli-0.1.2.dist-info/entry_points.txt
twofactorauthcli-0.1.2.dist-info/LICENSE
twofactorauthcli-0.1.2.dist-info/WHEEL
twofactorauthcli-0.1.2.dist-info/METADATA
twofactorauthcli-0.1.2.dist-info/RECORD
